previewer.py
link_previewer-0.0.6.dist-info/LICENCE.txt
link_previewer-0.0.6.dist-info/METADATA
link_previewer-0.0.6.dist-info/WHEEL
link_previewer-0.0.6.dist-info/top_level.txt
link_previewer-0.0.6.dist-info/RECORD
